templatepy/__init__.py
templatepy/example.data.file.config
templatepy/example.data.file.test-extension-yu48
tests/tests/test_integration/test_placeholder.py
tests/tests/test_unit/test_unit.py
templatepy-0.2.9.dist-info/LICENSE
templatepy-0.2.9.dist-info/METADATA
templatepy-0.2.9.dist-info/WHEEL
templatepy-0.2.9.dist-info/entry_points.txt
templatepy-0.2.9.dist-info/top_level.txt
templatepy-0.2.9.dist-info/RECORD
