Metadata-Version: 2.2
Name: templatepy
Version: 0.2.9
Summary: templatepy: Template repo for python repositories & PyPi integration
Author-email: "Lars B. Rollik" <L.B.Rollik@protonmail.com>
License: BSD 3-Clause License
Project-URL: Repository, https://github.com/larsrollik/templatepy
Project-URL: Issue Tracker, https://github.com/larsrollik/templatepy/issues
Classifier: Intended Audience :: Developers
Classifier: Topic :: Software Development :: Libraries :: Python Modules
Classifier: License :: OSI Approved :: BSD License
Classifier: Operating System :: OS Independent
Classifier: Programming Language :: Python
Classifier: Programming Language :: Python :: 3
Classifier: Programming Language :: Python :: 3.10
Classifier: Programming Language :: Python :: 3.11
Requires-Python: >=3.10
License-File: LICENSE
Requires-Dist: black
Provides-Extra: dev
Requires-Dist: black; extra == "dev"
Requires-Dist: bump2version; extra == "dev"
Requires-Dist: pytest-cov; extra == "dev"
Requires-Dist: pre-commit; extra == "dev"
Requires-Dist: flake8; extra == "dev"
Requires-Dist: toml; extra == "dev"
